pointstorm_dev/__init__.py
pointstorm_dev/__main__.py
pointstorm_dev/somemodule.py
tests/__init__.py
tests/test_myclass.py
tests/test_mysecondclass.py
pointstorm_dev-1.0.0.dist-info/LICENSE
pointstorm_dev-1.0.0.dist-info/METADATA
pointstorm_dev-1.0.0.dist-info/WHEEL
pointstorm_dev-1.0.0.dist-info/entry_points.txt
pointstorm_dev-1.0.0.dist-info/top_level.txt
pointstorm_dev-1.0.0.dist-info/RECORD
