Metadata-Version: 2.1
Name: pointstorm-dev
Version: 1.0.0
Summary: Lorem ipsum dolor fiat lux
Home-page: https://pointstorm.io
Author: Tesfa Shenkute
Author-email: legetesfa@gmail.com
License: vnfjvksdv
Platform: UNKNOWN
License-File: LICENSE
Requires-Dist: six
